dopy/__init__.py
dopy/cli.py
dopy/core.py
dopy/exceptions.py
dopy/help.py
dopy/run.py
dopy/transpiler/__init__.py
dopy/transpiler/collector.py
dopy/transpiler/processor.py
dopy_syntax-0.1.0.dist-info/LICENSE
dopy_syntax-0.1.0.dist-info/METADATA
dopy_syntax-0.1.0.dist-info/WHEEL
dopy_syntax-0.1.0.dist-info/entry_points.txt
dopy_syntax-0.1.0.dist-info/RECORD
