Metadata-Version: 2.1
Name: dopy-syntax
Version: 0.1.0
Summary: Transform Python code using do..end blocks instead of indentation-based scoping
Author: Navdeep Saini
Author-email: navdeep@mailbox.org
Requires-Python: >=3.10,<4.0
Classifier: Programming Language :: Python :: 3
Classifier: Programming Language :: Python :: 3.10
Classifier: Programming Language :: Python :: 3.11
Classifier: Programming Language :: Python :: 3.12
Requires-Dist: autopep8 (>=2.3.1,<3.0.0)
